torch_sparsify/__init__.py
torch_sparsify-1.0.dist-info/LICENSE
torch_sparsify-1.0.dist-info/METADATA
torch_sparsify-1.0.dist-info/WHEEL
torch_sparsify-1.0.dist-info/top_level.txt
torch_sparsify-1.0.dist-info/RECORD
